rostaing_ocr/__init__.py
rostaing_ocr/rostaing_ocr.py
rostaing_ocr-1.2.2.dist-info/licenses/LICENCE
rostaing_ocr-1.2.2.dist-info/METADATA
rostaing_ocr-1.2.2.dist-info/WHEEL
rostaing_ocr-1.2.2.dist-info/top_level.txt
rostaing_ocr-1.2.2.dist-info/RECORD
