Metadata-Version: 2.4
Name: rostaing-ocr
Version: 1.2.2
Summary: High-Precision OCR Extraction for LLMs and RAG Systems: PDFs, Scanned PDFs, and Images
Home-page: https://github.com/Rostaing/rostaing-ocr
Author: Davila Rostaing
Author-email: rostaingdavila@gmail.com
Classifier: Programming Language :: Python :: 3
Classifier: License :: OSI Approved :: MIT License
Classifier: Operating System :: OS Independent
Classifier: Topic :: Multimedia :: Graphics :: Capture :: Scanners
Classifier: Topic :: Scientific/Engineering :: Image Processing
Classifier: Topic :: Scientific/Engineering :: Artificial Intelligence
Classifier: Intended Audience :: Developers
Requires-Python: >=3.8
License-File: LICENCE
Requires-Dist: pymupdf>=1.20.0
Requires-Dist: python-doctr[torch]>=0.7.0
Requires-Dist: pillow>=9.0.0
Requires-Dist: numpy>=1.21.0
Dynamic: author
Dynamic: author-email
Dynamic: classifier
Dynamic: description
Dynamic: description-content-type
Dynamic: home-page
Dynamic: license-file
Dynamic: requires-dist
Dynamic: requires-python
Dynamic: summary
